{
    "os": "Linux-5.15.0-78-generic-x86_64-with-glibc2.35",
    "python": "3.12.3",
    "heartbeatAt": "2024-08-07T02:44:43.127220",
    "startedAt": "2024-08-07T02:44:41.147907",
    "docker": null,
    "cuda": null,
    "args": [],
    "state": "running",
    "program": "/root/imageCompare-py/CloudSeaScene/train.py",
    "codePathLocal": "CloudSeaScene/train.py",
    "codePath": "CloudSeaScene/train.py",
    "git": {
        "remote": "https://github.com/changyang-zeng66885/imageCompare-py.git",
        "commit": "5e30b303b0ff346e80d541ea9cc1e8bdb996eec2"
    },
    "email": "changyang.zeng@qq.com",
    "root": "/root/imageCompare-py",
    "host": "autodl-container-361446b3e2-7d06fdef",
    "username": "root",
    "executable": "/root/miniconda3/bin/python",
    "cpu_count": 28,
    "cpu_count_logical": 56,
    "cpu_freq": {
        "current": 1634.5979642857142,
        "min": 1200.0,
        "max": 3300.0
    },
    "cpu_freq_per_core": [
        {
            "current": 1200.0,
            "min": 1200.0,
            "max": 3300.0
        },
        {
            "current": 1200.0,
            "min": 1200.0,
            "max": 3300.0
        },
        {
            "current": 1200.0,
            "min": 1200.0,
            "max": 3300.0
        },
        {
            "current": 1200.0,
            "min": 1200.0,
            "max": 3300.0
        },
        {
            "current": 1200.0,
            "min": 1200.0,
            "max": 3300.0
        },
        {
            "current": 1200.0,
            "min": 1200.0,
            "max": 3300.0
        },
        {
            "current": 3152.22,
            "min": 1200.0,
            "max": 3300.0
        },
        {
            "current": 3300.0,
            "min": 1200.0,
            "max": 3300.0
        },
        {
            "current": 1200.0,
            "min": 1200.0,
            "max": 3300.0
        },
        {
            "current": 3300.0,
            "min": 1200.0,
            "max": 3300.0
        },
        {
            "current": 1200.0,
            "min": 1200.0,
            "max": 3300.0
        },
        {
            "current": 1235.595,
            "min": 1200.0,
            "max": 3300.0
        },
        {
            "current": 1200.0,
            "min": 1200.0,
            "max": 3300.0
        },
        {
            "current": 1200.0,
            "min": 1200.0,
            "max": 3300.0
        },
        {
            "current": 1200.0,
            "min": 1200.0,
            "max": 3300.0
        },
        {
            "current": 1200.0,
            "min": 1200.0,
            "max": 3300.0
        },
        {
            "current": 1200.0,
            "min": 1200.0,
            "max": 3300.0
        },
        {
            "current": 1200.0,
            "min": 1200.0,
            "max": 3300.0
        },
        {
            "current": 1200.0,
            "min": 1200.0,
            "max": 3300.0
        },
        {
            "current": 1200.0,
            "min": 1200.0,
            "max": 3300.0
        },
        {
            "current": 2345.226,
            "min": 1200.0,
            "max": 3300.0
        },
        {
            "current": 1200.0,
            "min": 1200.0,
            "max": 3300.0
        },
        {
            "current": 1200.0,
            "min": 1200.0,
            "max": 3300.0
        },
        {
            "current": 1200.0,
            "min": 1200.0,
            "max": 3300.0
        },
        {
            "current": 1200.0,
            "min": 1200.0,
            "max": 3300.0
        },
        {
            "current": 1200.0,
            "min": 1200.0,
            "max": 3300.0
        },
        {
            "current": 2338.552,
            "min": 1200.0,
            "max": 3300.0
        },
        {
            "current": 1200.0,
            "min": 1200.0,
            "max": 3300.0
        },
        {
            "current": 1200.0,
            "min": 1200.0,
            "max": 3300.0
        },
        {
            "current": 1200.0,
            "min": 1200.0,
            "max": 3300.0
        },
        {
            "current": 1200.0,
            "min": 1200.0,
            "max": 3300.0
        },
        {
            "current": 1200.0,
            "min": 1200.0,
            "max": 3300.0
        },
        {
            "current": 1200.0,
            "min": 1200.0,
            "max": 3300.0
        },
        {
            "current": 2100.0,
            "min": 1200.0,
            "max": 3300.0
        },
        {
            "current": 1200.0,
            "min": 1200.0,
            "max": 3300.0
        },
        {
            "current": 1200.0,
            "min": 1200.0,
            "max": 3300.0
        },
        {
            "current": 1200.0,
            "min": 1200.0,
            "max": 3300.0
        },
        {
            "current": 1200.0,
            "min": 1200.0,
            "max": 3300.0
        },
        {
            "current": 1200.0,
            "min": 1200.0,
            "max": 3300.0
        },
        {
            "current": 1200.0,
            "min": 1200.0,
            "max": 3300.0
        },
        {
            "current": 1200.0,
            "min": 1200.0,
            "max": 3300.0
        },
        {
            "current": 1200.0,
            "min": 1200.0,
            "max": 3300.0
        },
        {
            "current": 3300.0,
            "min": 1200.0,
            "max": 3300.0
        },
        {
            "current": 2300.005,
            "min": 1200.0,
            "max": 3300.0
        },
        {
            "current": 1200.0,
            "min": 1200.0,
            "max": 3300.0
        },
        {
            "current": 1200.0,
            "min": 1200.0,
            "max": 3300.0
        },
        {
            "current": 2845.392,
            "min": 1200.0,
            "max": 3300.0
        },
        {
            "current": 2239.6,
            "min": 1200.0,
            "max": 3300.0
        },
        {
            "current": 1200.0,
            "min": 1200.0,
            "max": 3300.0
        },
        {
            "current": 1200.0,
            "min": 1200.0,
            "max": 3300.0
        },
        {
            "current": 1200.0,
            "min": 1200.0,
            "max": 3300.0
        },
        {
            "current": 1200.0,
            "min": 1200.0,
            "max": 3300.0
        },
        {
            "current": 2500.0,
            "min": 1200.0,
            "max": 3300.0
        },
        {
            "current": 1200.0,
            "min": 1200.0,
            "max": 3300.0
        },
        {
            "current": 1200.0,
            "min": 1200.0,
            "max": 3300.0
        },
        {
            "current": 2500.0,
            "min": 1200.0,
            "max": 3300.0
        }
    ],
    "disk": {
        "/": {
            "total": 30.0,
            "used": 2.914886474609375
        }
    },
    "gpu": "NVIDIA GeForce RTX 3080",
    "gpu_count": 1,
    "gpu_devices": [
        {
            "name": "NVIDIA GeForce RTX 3080",
            "memory_total": 21474836480
        }
    ],
    "memory": {
        "total": 251.76569747924805
    }
}
